Workbook

Sheet Dashboard
B2: Harbor & Pine Outdoor Co. — Sales & Profit Dashboard | N2: Built by Md Muntasir Mamun Mojumder
B3: ="Year to date: "&Calc!$C$9&" · US$ · compared with the same months a year earlier · fictional demo data" -> Year to date: Jan–Oct 2026 · US$ · compared with the same months a year earlier · fictional demo data
B6: Year ▸ | C6: 2026 | E6: Region ▸ | F6: All regions | H6: Channel ▸ | I6: All channels | K6: Category ▸ | L6: All categories | O6: ◂ Pick filters: everything updates
B8: Net revenue | E8: Gross profit | H8: Gross margin | K8: Orders | N8: Return rate | Q8: Marketing ROAS
B9: =Calc!C12 -> 4416619 | E9: =Calc!C13 -> 2283498 | H9: =Calc!C14 -> 0.517024 | K9: =Calc!C15 -> 45955 | N9: =Calc!C17 -> 0.073152362 | Q9: =Calc!C19 -> 6.3538053
B10: =IF(OR(NOT(Calc!$C$8),Calc!D12=0),"No "&(Calc!$C$3-1)&" data to compare",IF(ABS(Calc!C12/Calc!D12-1)<0.0005,"● Same as "&(Calc!$C$3-1),IF(Calc!C12>=Calc!D12,"▲ ","▼ ")&TEXT(ABS(Calc!C12/Calc!D12-1),"0.0%")&" vs "&(Calc!$C$3-1))) -> ▲ 16.2% vs 2025 | E10: =IF(OR(NOT(Calc!$C$8),Calc!D13=0),"No "&(Calc!$C$3-1)&" data to compare",IF(ABS(Calc!C13/Calc!D13-1)<0.0005,"● Same as "&(Calc!$C$3-1),IF(Calc!C13>=Calc!D13,"▲ ","▼ ")&TEXT(ABS(Calc!C13/Calc!D13-1),"0.0%")&" vs "&(Calc!$C$3-1))) -> ▲ 16.0% vs 2025 | H10: =IF(OR(NOT(Calc!$C$8),Calc!D14=0),"No "&(Calc!$C$3-1)&" data to compare",IF(ABS(Calc!C14-Calc!D14)<0.0005,"● Same as "&(Calc!$C$3-1),IF(Calc!C14>=Calc!D14,"▲ ","▼ ")&TEXT(ABS(Calc!C14-Calc!D14)*100,"0.0")&" pts"&" vs "&(Calc!$C$3-1))) -> ▼ 0.1 pts vs 2025 | K10: =IF(OR(NOT(Calc!$C$8),Calc!D15=0),"No "&(Calc!$C$3-1)&" data to compare",IF(ABS(Calc!C15/Calc!D15-1)<0.0005,"● Same as "&(Calc!$C$3-1),IF(Calc!C15>=Calc!D15,"▲ ","▼ ")&TEXT(ABS(Calc!C15/Calc!D15-1),"0.0%")&" vs "&(Calc!$C$3-1))) -> ▲ 16.2% vs 2025 | N10: =IF(OR(NOT(Calc!$C$8),Calc!D17=0),"No "&(Calc!$C$3-1)&" data to compare",IF(ABS(Calc!C17-Calc!D17)<0.0005,"● Same as "&(Calc!$C$3-1),IF(Calc!C17>=Calc!D17,"▲ ","▼ ")&TEXT(ABS(Calc!C17-Calc!D17)*100,"0.0")&" pts"&" vs "&(Calc!$C$3-1))) -> ● Same as 2025 | Q10: =IF(OR(NOT(Calc!$C$8),Calc!D19=0),"No "&(Calc!$C$3-1)&" data to compare",IF(ABS(Calc!C19/Calc!D19-1)<0.0005,"● Same as "&(Calc!$C$3-1),IF(Calc!C19>=Calc!D19,"▲ ","▼ ")&TEXT(ABS(Calc!C19-Calc!D19),"0.0")&"x"&" vs "&(Calc!$C$3-1))) -> ▼ 0.2x vs 2025
B45: Category performance (year to date · region & channel filters apply)
B46: Category | E46: Net revenue | H46: Prior year | K46: YoY change | N46: Gross margin | Q46: Return rate
B47: =Calc!B38 -> Tents & Shelter | E47: =Calc!C38 -> 1105774 | H47: =Calc!D38 -> 945467 | K47: =Calc!E38 -> 0.16955325 | N47: =Calc!F38 -> 0.46504982 | Q47: =Calc!G38 -> 0.041177945
B48: =Calc!B39 -> Backpacks | E48: =Calc!C39 -> 944212 | H48: =Calc!D39 -> 820493 | K48: =Calc!E39 -> 0.15078617 | N48: =Calc!F39 -> 0.54264614 | Q48: =Calc!G39 -> 0.051088993
B49: =Calc!B40 -> Apparel | E49: =Calc!C40 -> 1062047 | H49: =Calc!D40 -> 915813 | K49: =Calc!E40 -> 0.1596767 | N49: =Calc!F40 -> 0.60176527 | Q49: =Calc!G40 -> 0.1036746
B50: =Calc!B41 -> Footwear | E50: =Calc!C41 -> 744196 | H50: =Calc!D41 -> 638906 | K50: =Calc!E41 -> 0.16479733 | N50: =Calc!F41 -> 0.44405909 | Q50: =Calc!G41 -> 0.12810852
B51: =Calc!B42 -> Camp Kitchen | E51: =Calc!C42 -> 560390 | H51: =Calc!D42 -> 480000 | K51: =Calc!E42 -> 0.16747917 | N51: =Calc!F42 -> 0.51270544 | Q51: =Calc!G42 -> 0.031241464
B52: Total | E52: =SUM(E47:E51) -> 4416619 | H52: =SUM(H47:H51) -> 3800679 | K52: =IF(H52=0,"",E52/H52-1) -> 0.16206052 | N52: =IF(E52=0,0,SUMPRODUCT(E47:E51,N47:N51)/E52) -> 0.517024 | Q52: =IFERROR(SUMIFS(Sales!$K$2:$K$1321,Sales!$B$2:$B$1321,Calc!$C$3,Sales!$C$2:$C$1321,"<="&Calc!$C$7,Sales!$E$2:$E$1321,Calc!$C$4,Sales!$F$2:$F$1321,Calc!$C$5)/SUMIFS(Sales!$J$2:$J$1321,Sales!$B$2:$B$1321,Calc!$C$3,Sales!$C$2:$C$1321,"<="&Calc!$C$7,Sales!$E$2:$E$1321,Calc!$C$4,Sales!$F$2:$F$1321,Calc!$C$5),0) -> 0.073152362
B54: Net revenue = gross revenue − returns. Gross margin = gross profit ÷ net revenue. Return rates of 8% or more are highlighted. 2026 runs to October, so it is compared with Jan–Oct 2025.

Sheet Sales
A1: Month | B1: Year | C1: Month # | D1: Month name | E1: Region | F1: Channel | G1: Category | H1: Orders | I1: Units | J1: Gross revenue ($) | K1: Returns ($) | L1: Net revenue ($) | M1: COGS ($) | N1: Gross profit ($)
A2: 45658 | B2: 2025 | C2: 1 | D2: Jan | E2: West | F2: Online store | G2: Tents & Shelter | H2: 48 | I2: 58 | J2: 9071 | K2: 385 | L2: =J2-K2 -> 8686 | M2: 4486 | N2: =L2-M2 -> 4200
A3: 45658 | B3: 2025 | C3: 1 | D3: Jan | E3: West | F3: Online store | G3: Backpacks | H3: 75 | I3: 99 | J3: 8433 | K3: 347 | L3: =J3-K3 -> 8086 | M3: 3640 | N3: =L3-M3 -> 4446
A4: 45658 | B4: 2025 | C4: 1 | D4: Jan | E4: West | F4: Online store | G4: Apparel | H4: 103 | I4: 139 | J4: 8652 | K4: 716 | L4: =J4-K4 -> 7936 | M4: 3019 | N4: =L4-M4 -> 4917
A5: 45658 | B5: 2025 | C5: 1 | D5: Jan | E5: West | F5: Online store | G5: Footwear | H5: 55 | I5: 84 | J5: 7005 | K5: 714 | L5: =J5-K5 -> 6291 | M5: 3403 | N5: =L5-M5 -> 2888
A6: 45658 | B6: 2025 | C6: 1 | D6: Jan | E6: West | F6: Online store | G6: Camp Kitchen | H6: 81 | I6: 128 | J6: 4941 | K6: 153 | L6: =J6-K6 -> 4788 | M6: 2284 | N6: =L6-M6 -> 2504
A7: 45658 | B7: 2025 | C7: 1 | D7: Jan | E7: West | F7: Amazon | G7: Tents & Shelter | H7: 43 | I7: 50 | J7: 7523 | K7: 464 | L7: =J7-K7 -> 7059 | M7: 3825 | N7: =L7-M7 -> 3234
A8: 45658 | B8: 2025 | C8: 1 | D8: Jan | E8: West | F8: Amazon | G8: Backpacks | H8: 51 | I8: 61 | J8: 5229 | K8: 326 | L8: =J8-K8 -> 4903 | M8: 2358 | N8: =L8-M8 -> 2545
A9: 45658 | B9: 2025 | C9: 1 | D9: Jan | E9: West | F9: Amazon | G9: Apparel | H9: 81 | I9: 114 | J9: 6296 | K9: 897 | L9: =J9-K9 -> 5399 | M9: 2220 | N9: =L9-M9 -> 3179
A10: 45658 | B10: 2025 | C10: 1 | D10: Jan | E10: West | F10: Amazon | G10: Footwear | H10: 43 | I10: 51 | J10: 5045 | K10: 673 | L10: =J10-K10 -> 4372 | M10: 2439 | N10: =L10-M10 -> 1933
A11: 45658 | B11: 2025 | C11: 1 | D11: Jan | E11: West | F11: Amazon | G11: Camp Kitchen | H11: 62 | I11: 83 | J11: 3486 | K11: 131 | L11: =J11-K11 -> 3355 | M11: 1689 | N11: =L11-M11 -> 1666
A12: 45658 | B12: 2025 | C12: 1 | D12: Jan | E12: West | F12: Retail store | G12: Tents & Shelter | H12: 22 | I12: 28 | J12: 4504 | K12: 141 | L12: =J12-K12 -> 4363 | M12: 2340 | N12: =L12-M12 -> 2023
A13: 45658 | B13: 2025 | C13: 1 | D13: Jan | E13: West | F13: Retail store | G13: Backpacks | H13: 31 | I13: 44 | J13: 3707 | K13: 131 | L13: =J13-K13 -> 3576 | M13: 1645 | N13: =L13-M13 -> 1931
... A1321: 46296 | B1321: 2026 | C1321: 10 | D1321: Oct | E1321: Midwest | F1321: Retail store | G1321: Camp Kitchen | H1321: 31 | I1321: 36 | J1321: 1989 | K1321: 49 | L1321: =J1321-K1321 -> 1940 | M1321: 932 | N1321: =L1321-M1321 -> 1008

Sheet Marketing
A1: Month | B1: Year | C1: Month # | D1: Month name | E1: Channel | F1: Ad spend ($)
A2: 45658 | B2: 2025 | C2: 1 | D2: Jan | E2: Online store | F2: 19748
A3: 45658 | B3: 2025 | C3: 1 | D3: Jan | E3: Amazon | F3: 9739
A4: 45658 | B4: 2025 | C4: 1 | D4: Jan | E4: Retail store | F4: 3425
A5: 45689 | B5: 2025 | C5: 2 | D5: Feb | E5: Online store | F5: 23026
A6: 45689 | B6: 2025 | C6: 2 | D6: Feb | E6: Amazon | F6: 12950
A7: 45689 | B7: 2025 | C7: 2 | D7: Feb | E7: Retail store | F7: 4345
A8: 45717 | B8: 2025 | C8: 3 | D8: Mar | E8: Online store | F8: 24991
A9: 45717 | B9: 2025 | C9: 3 | D9: Mar | E9: Amazon | F9: 14433
A10: 45717 | B10: 2025 | C10: 3 | D10: Mar | E10: Retail store | F10: 5215
A11: 45748 | B11: 2025 | C11: 4 | D11: Apr | E11: Online store | F11: 33846
A12: 45748 | B12: 2025 | C12: 4 | D12: Apr | E12: Amazon | F12: 19826
A13: 45748 | B13: 2025 | C13: 4 | D13: Apr | E13: Retail store | F13: 5879
... A67: 46296 | B67: 2026 | C67: 10 | D67: Oct | E67: Retail store | F67: 6709

Sheet Calc
A1: Helper calculations for the dashboard (do not edit). Filters come from the Dashboard dropdowns.
B3: Year | C3: =Dashboard!$C$6 -> 2026
B4: Region filter | C4: =IF(Dashboard!$F$6="All regions","*",Dashboard!$F$6) -> *
B5: Channel filter | C5: =IF(Dashboard!$I$6="All channels","*",Dashboard!$I$6) -> *
B6: Category filter | C6: =IF(Dashboard!$L$6="All categories","*",Dashboard!$L$6) -> *
B7: Last month with data | C7: =SUMPRODUCT(MAX((Sales!$B$2:$B$1321=$C$3)*Sales!$C$2:$C$1321)) -> 10
B8: Prior year has data? | C8: =COUNTIF(Sales!$B$2:$B$1321,$C$3-1)>0 -> 1
B9: Period label | C9: =IF($C$7=12,"Full year "&$C$3,"Jan–"&TEXT(DATE($C$3,$C$7,1),"mmm")&" "&$C$3) -> Jan–Oct 2026
B11: KPI (year to date) | C11: Selected year | D11: Same months, prior year
B12: Net revenue | C12: =SUMIFS(Sales!$L$2:$L$1321,Sales!$B$2:$B$1321,$C$3,Sales!$C$2:$C$1321,"<="&$C$7,Sales!$E$2:$E$1321,$C$4,Sales!$F$2:$F$1321,$C$5,Sales!$G$2:$G$1321,$C$6) -> 4416619 | D12: =SUMIFS(Sales!$L$2:$L$1321,Sales!$B$2:$B$1321,$C$3-1,Sales!$C$2:$C$1321,"<="&$C$7,Sales!$E$2:$E$1321,$C$4,Sales!$F$2:$F$1321,$C$5,Sales!$G$2:$G$1321,$C$6) -> 3800679
B13: Gross profit | C13: =SUMIFS(Sales!$N$2:$N$1321,Sales!$B$2:$B$1321,$C$3,Sales!$C$2:$C$1321,"<="&$C$7,Sales!$E$2:$E$1321,$C$4,Sales!$F$2:$F$1321,$C$5,Sales!$G$2:$G$1321,$C$6) -> 2283498 | D13: =SUMIFS(Sales!$N$2:$N$1321,Sales!$B$2:$B$1321,$C$3-1,Sales!$C$2:$C$1321,"<="&$C$7,Sales!$E$2:$E$1321,$C$4,Sales!$F$2:$F$1321,$C$5,Sales!$G$2:$G$1321,$C$6) -> 1968838
B14: Gross margin | C14: =IF(C12=0,0,C13/C12) -> 0.517024 | D14: =IF(D12=0,0,D13/D12) -> 0.5180227
B15: Orders | C15: =SUMIFS(Sales!$H$2:$H$1321,Sales!$B$2:$B$1321,$C$3,Sales!$C$2:$C$1321,"<="&$C$7,Sales!$E$2:$E$1321,$C$4,Sales!$F$2:$F$1321,$C$5,Sales!$G$2:$G$1321,$C$6) -> 45955 | D15: =SUMIFS(Sales!$H$2:$H$1321,Sales!$B$2:$B$1321,$C$3-1,Sales!$C$2:$C$1321,"<="&$C$7,Sales!$E$2:$E$1321,$C$4,Sales!$F$2:$F$1321,$C$5,Sales!$G$2:$G$1321,$C$6) -> 39552
B16: Average order value | C16: =IF(C15=0,0,C12/C15) -> 96.107475 | D16: =IF(D15=0,0,D12/D15) -> 96.093219
B17: Return rate | C17: =IFERROR(SUMIFS(Sales!$K$2:$K$1321,Sales!$B$2:$B$1321,$C$3,Sales!$C$2:$C$1321,"<="&$C$7,Sales!$E$2:$E$1321,$C$4,Sales!$F$2:$F$1321,$C$5,Sales!$G$2:$G$1321,$C$6)/SUMIFS(Sales!$J$2:$J$1321,Sales!$B$2:$B$1321,$C$3,Sales!$C$2:$C$1321,"<="&$C$7,Sales!$E$2:$E$1321,$C$4,Sales!$F$2:$F$1321,$C$5,Sales!$G$2:$G$1321,$C$6),0) -> 0.073152362 | D17: =IFERROR(SUMIFS(Sales!$K$2:$K$1321,Sales!$B$2:$B$1321,$C$3-1,Sales!$C$2:$C$1321,"<="&$C$7,Sales!$E$2:$E$1321,$C$4,Sales!$F$2:$F$1321,$C$5,Sales!$G$2:$G$1321,$C$6)/SUMIFS(Sales!$J$2:$J$1321,Sales!$B$2:$B$1321,$C$3-1,Sales!$C$2:$C$1321,"<="&$C$7,Sales!$E$2:$E$1321,$C$4,Sales!$F$2:$F$1321,$C$5,Sales!$G$2:$G$1321,$C$6),0) -> 0.073131267
B18: Ad spend | C18: =SUMIFS(Marketing!$F$2:$F$67,Marketing!$B$2:$B$67,$C$3,Marketing!$C$2:$C$67,"<="&$C$7,Marketing!$E$2:$E$67,$C$5) -> 695114 | D18: =SUMIFS(Marketing!$F$2:$F$67,Marketing!$B$2:$B$67,$C$3-1,Marketing!$C$2:$C$67,"<="&$C$7,Marketing!$E$2:$E$67,$C$5) -> 576651
B19: Marketing ROAS | C19: =IFERROR(SUMIFS(Sales!$L$2:$L$1321,Sales!$B$2:$B$1321,$C$3,Sales!$C$2:$C$1321,"<="&$C$7,Sales!$F$2:$F$1321,$C$5)/C18,0) -> 6.3538053 | D19: =IFERROR(SUMIFS(Sales!$L$2:$L$1321,Sales!$B$2:$B$1321,$C$3-1,Sales!$C$2:$C$1321,"<="&$C$7,Sales!$F$2:$F$1321,$C$5)/D18,0) -> 6.5909519
B22: Month | C22: =$C$3 -> 2026 | D22: =$C$3-1 -> 2025 | E22: Ad spend | F22: ROAS | G22: Month # | I22: Channel | J22: Net revenue | L22: Region | M22: Net revenue
B23: Jan | C23: =SUMIFS(Sales!$L$2:$L$1321,Sales!$B$2:$B$1321,$C$3,Sales!$C$2:$C$1321,G23,Sales!$E$2:$E$1321,$C$4,Sales!$F$2:$F$1321,$C$5,Sales!$G$2:$G$1321,$C$6) -> 262085 | D23: =SUMIFS(Sales!$L$2:$L$1321,Sales!$B$2:$B$1321,$C$3-1,Sales!$C$2:$C$1321,G23,Sales!$E$2:$E$1321,$C$4,Sales!$F$2:$F$1321,$C$5,Sales!$G$2:$G$1321,$C$6) -> 231322 | E23: =SUMIFS(Marketing!$F$2:$F$67,Marketing!$B$2:$B$67,$C$3,Marketing!$C$2:$C$67,G23,Marketing!$E$2:$E$67,$C$5) -> 41344 | F23: =IF(E23=0,0,SUMIFS(Sales!$L$2:$L$1321,Sales!$B$2:$B$1321,$C$3,Sales!$C$2:$C$1321,G23,Sales!$F$2:$F$1321,$C$5)/E23) -> 6.3391302 | G23: 1 | I23: Online store | J23: =SUMIFS(Sales!$L$2:$L$1321,Sales!$B$2:$B$1321,$C$3,Sales!$C$2:$C$1321,"<="&$C$7,Sales!$E$2:$E$1321,$C$4,Sales!$F$2:$F$1321,I23,Sales!$G$2:$G$1321,$C$6) -> 2045447 | L23: West | M23: =SUMIFS(Sales!$L$2:$L$1321,Sales!$B$2:$B$1321,$C$3,Sales!$C$2:$C$1321,"<="&$C$7,Sales!$E$2:$E$1321,L23,Sales!$F$2:$F$1321,$C$5,Sales!$G$2:$G$1321,$C$6) -> 1502212
B24: Feb | C24: =SUMIFS(Sales!$L$2:$L$1321,Sales!$B$2:$B$1321,$C$3,Sales!$C$2:$C$1321,G24,Sales!$E$2:$E$1321,$C$4,Sales!$F$2:$F$1321,$C$5,Sales!$G$2:$G$1321,$C$6) -> 286475 | D24: =SUMIFS(Sales!$L$2:$L$1321,Sales!$B$2:$B$1321,$C$3-1,Sales!$C$2:$C$1321,G24,Sales!$E$2:$E$1321,$C$4,Sales!$F$2:$F$1321,$C$5,Sales!$G$2:$G$1321,$C$6) -> 242525 | E24: =SUMIFS(Marketing!$F$2:$F$67,Marketing!$B$2:$B$67,$C$3,Marketing!$C$2:$C$67,G24,Marketing!$E$2:$E$67,$C$5) -> 46267 | F24: =IF(E24=0,0,SUMIFS(Sales!$L$2:$L$1321,Sales!$B$2:$B$1321,$C$3,Sales!$C$2:$C$1321,G24,Sales!$F$2:$F$1321,$C$5)/E24) -> 6.1917782 | G24: 2 | I24: Amazon | J24: =SUMIFS(Sales!$L$2:$L$1321,Sales!$B$2:$B$1321,$C$3,Sales!$C$2:$C$1321,"<="&$C$7,Sales!$E$2:$E$1321,$C$4,Sales!$F$2:$F$1321,I24,Sales!$G$2:$G$1321,$C$6) -> 1377367 | L24: South | M24: =SUMIFS(Sales!$L$2:$L$1321,Sales!$B$2:$B$1321,$C$3,Sales!$C$2:$C$1321,"<="&$C$7,Sales!$E$2:$E$1321,L24,Sales!$F$2:$F$1321,$C$5,Sales!$G$2:$G$1321,$C$6) -> 1201313
B25: Mar | C25: =SUMIFS(Sales!$L$2:$L$1321,Sales!$B$2:$B$1321,$C$3,Sales!$C$2:$C$1321,G25,Sales!$E$2:$E$1321,$C$4,Sales!$F$2:$F$1321,$C$5,Sales!$G$2:$G$1321,$C$6) -> 365274 | D25: =SUMIFS(Sales!$L$2:$L$1321,Sales!$B$2:$B$1321,$C$3-1,Sales!$C$2:$C$1321,G25,Sales!$E$2:$E$1321,$C$4,Sales!$F$2:$F$1321,$C$5,Sales!$G$2:$G$1321,$C$6) -> 313167 | E25: =SUMIFS(Marketing!$F$2:$F$67,Marketing!$B$2:$B$67,$C$3,Marketing!$C$2:$C$67,G25,Marketing!$E$2:$E$67,$C$5) -> 56285 | F25: =IF(E25=0,0,SUMIFS(Sales!$L$2:$L$1321,Sales!$B$2:$B$1321,$C$3,Sales!$C$2:$C$1321,G25,Sales!$F$2:$F$1321,$C$5)/E25) -> 6.489722 | G25: 3 | I25: Retail store | J25: =SUMIFS(Sales!$L$2:$L$1321,Sales!$B$2:$B$1321,$C$3,Sales!$C$2:$C$1321,"<="&$C$7,Sales!$E$2:$E$1321,$C$4,Sales!$F$2:$F$1321,I25,Sales!$G$2:$G$1321,$C$6) -> 993805 | L25: Northeast | M25: =SUMIFS(Sales!$L$2:$L$1321,Sales!$B$2:$B$1321,$C$3,Sales!$C$2:$C$1321,"<="&$C$7,Sales!$E$2:$E$1321,L25,Sales!$F$2:$F$1321,$C$5,Sales!$G$2:$G$1321,$C$6) -> 871395
B26: Apr | C26: =SUMIFS(Sales!$L$2:$L$1321,Sales!$B$2:$B$1321,$C$3,Sales!$C$2:$C$1321,G26,Sales!$E$2:$E$1321,$C$4,Sales!$F$2:$F$1321,$C$5,Sales!$G$2:$G$1321,$C$6) -> 423467 | D26: =SUMIFS(Sales!$L$2:$L$1321,Sales!$B$2:$B$1321,$C$3-1,Sales!$C$2:$C$1321,G26,Sales!$E$2:$E$1321,$C$4,Sales!$F$2:$F$1321,$C$5,Sales!$G$2:$G$1321,$C$6) -> 369220 | E26: =SUMIFS(Marketing!$F$2:$F$67,Marketing!$B$2:$B$67,$C$3,Marketing!$C$2:$C$67,G26,Marketing!$E$2:$E$67,$C$5) -> 63335 | F26: =IF(E26=0,0,SUMIFS(Sales!$L$2:$L$1321,Sales!$B$2:$B$1321,$C$3,Sales!$C$2:$C$1321,G26,Sales!$F$2:$F$1321,$C$5)/E26) -> 6.6861451 | G26: 4 | L26: Midwest | M26: =SUMIFS(Sales!$L$2:$L$1321,Sales!$B$2:$B$1321,$C$3,Sales!$C$2:$C$1321,"<="&$C$7,Sales!$E$2:$E$1321,L26,Sales!$F$2:$F$1321,$C$5,Sales!$G$2:$G$1321,$C$6) -> 841699
B27: May | C27: =SUMIFS(Sales!$L$2:$L$1321,Sales!$B$2:$B$1321,$C$3,Sales!$C$2:$C$1321,G27,Sales!$E$2:$E$1321,$C$4,Sales!$F$2:$F$1321,$C$5,Sales!$G$2:$G$1321,$C$6) -> 519017 | D27: =SUMIFS(Sales!$L$2:$L$1321,Sales!$B$2:$B$1321,$C$3-1,Sales!$C$2:$C$1321,G27,Sales!$E$2:$E$1321,$C$4,Sales!$F$2:$F$1321,$C$5,Sales!$G$2:$G$1321,$C$6) -> 444968 | E27: =SUMIFS(Marketing!$F$2:$F$67,Marketing!$B$2:$B$67,$C$3,Marketing!$C$2:$C$67,G27,Marketing!$E$2:$E$67,$C$5) -> 86018 | F27: =IF(E27=0,0,SUMIFS(Sales!$L$2:$L$1321,Sales!$B$2:$B$1321,$C$3,Sales!$C$2:$C$1321,G27,Sales!$F$2:$F$1321,$C$5)/E27) -> 6.0338185 | G27: 5
B28: Jun | C28: =SUMIFS(Sales!$L$2:$L$1321,Sales!$B$2:$B$1321,$C$3,Sales!$C$2:$C$1321,G28,Sales!$E$2:$E$1321,$C$4,Sales!$F$2:$F$1321,$C$5,Sales!$G$2:$G$1321,$C$6) -> 591489 | D28: =SUMIFS(Sales!$L$2:$L$1321,Sales!$B$2:$B$1321,$C$3-1,Sales!$C$2:$C$1321,G28,Sales!$E$2:$E$1321,$C$4,Sales!$F$2:$F$1321,$C$5,Sales!$G$2:$G$1321,$C$6) -> 494774 | E28: =SUMIFS(Marketing!$F$2:$F$67,Marketing!$B$2:$B$67,$C$3,Marketing!$C$2:$C$67,G28,Marketing!$E$2:$E$67,$C$5) -> 96789 | F28: =IF(E28=0,0,SUMIFS(Sales!$L$2:$L$1321,Sales!$B$2:$B$1321,$C$3,Sales!$C$2:$C$1321,G28,Sales!$F$2:$F$1321,$C$5)/E28) -> 6.111118 | G28: 6
B29: Jul | C29: =SUMIFS(Sales!$L$2:$L$1321,Sales!$B$2:$B$1321,$C$3,Sales!$C$2:$C$1321,G29,Sales!$E$2:$E$1321,$C$4,Sales!$F$2:$F$1321,$C$5,Sales!$G$2:$G$1321,$C$6) -> 596812 | D29: =SUMIFS(Sales!$L$2:$L$1321,Sales!$B$2:$B$1321,$C$3-1,Sales!$C$2:$C$1321,G29,Sales!$E$2:$E$1321,$C$4,Sales!$F$2:$F$1321,$C$5,Sales!$G$2:$G$1321,$C$6) -> 524284 | E29: =SUMIFS(Marketing!$F$2:$F$67,Marketing!$B$2:$B$67,$C$3,Marketing!$C$2:$C$67,G29,Marketing!$E$2:$E$67,$C$5) -> 88032 | F29: =IF(E29=0,0,SUMIFS(Sales!$L$2:$L$1321,Sales!$B$2:$B$1321,$C$3,Sales!$C$2:$C$1321,G29,Sales!$F$2:$F$1321,$C$5)/E29) -> 6.7794893 | G29: 7
B30: Aug | C30: =SUMIFS(Sales!$L$2:$L$1321,Sales!$B$2:$B$1321,$C$3,Sales!$C$2:$C$1321,G30,Sales!$E$2:$E$1321,$C$4,Sales!$F$2:$F$1321,$C$5,Sales!$G$2:$G$1321,$C$6) -> 547935 | D30: =SUMIFS(Sales!$L$2:$L$1321,Sales!$B$2:$B$1321,$C$3-1,Sales!$C$2:$C$1321,G30,Sales!$E$2:$E$1321,$C$4,Sales!$F$2:$F$1321,$C$5,Sales!$G$2:$G$1321,$C$6) -> 473279 | E30: =SUMIFS(Marketing!$F$2:$F$67,Marketing!$B$2:$B$67,$C$3,Marketing!$C$2:$C$67,G30,Marketing!$E$2:$E$67,$C$5) -> 86482 | F30: =IF(E30=0,0,SUMIFS(Sales!$L$2:$L$1321,Sales!$B$2:$B$1321,$C$3,Sales!$C$2:$C$1321,G30,Sales!$F$2:$F$1321,$C$5)/E30) -> 6.3358271 | G30: 8
B31: Sep | C31: =SUMIFS(Sales!$L$2:$L$1321,Sales!$B$2:$B$1321,$C$3,Sales!$C$2:$C$1321,G31,Sales!$E$2:$E$1321,$C$4,Sales!$F$2:$F$1321,$C$5,Sales!$G$2:$G$1321,$C$6) -> 440920 | D31: =SUMIFS(Sales!$L$2:$L$1321,Sales!$B$2:$B$1321,$C$3-1,Sales!$C$2:$C$1321,G31,Sales!$E$2:$E$1321,$C$4,Sales!$F$2:$F$1321,$C$5,Sales!$G$2:$G$1321,$C$6) -> 376845 | E31: =SUMIFS(Marketing!$F$2:$F$67,Marketing!$B$2:$B$67,$C$3,Marketing!$C$2:$C$67,G31,Marketing!$E$2:$E$67,$C$5) -> 68717 | F31: =IF(E31=0,0,SUMIFS(Sales!$L$2:$L$1321,Sales!$B$2:$B$1321,$C$3,Sales!$C$2:$C$1321,G31,Sales!$F$2:$F$1321,$C$5)/E31) -> 6.4164617 | G31: 9
B32: Oct | C32: =SUMIFS(Sales!$L$2:$L$1321,Sales!$B$2:$B$1321,$C$3,Sales!$C$2:$C$1321,G32,Sales!$E$2:$E$1321,$C$4,Sales!$F$2:$F$1321,$C$5,Sales!$G$2:$G$1321,$C$6) -> 383145 | D32: =SUMIFS(Sales!$L$2:$L$1321,Sales!$B$2:$B$1321,$C$3-1,Sales!$C$2:$C$1321,G32,Sales!$E$2:$E$1321,$C$4,Sales!$F$2:$F$1321,$C$5,Sales!$G$2:$G$1321,$C$6) -> 330295 | E32: =SUMIFS(Marketing!$F$2:$F$67,Marketing!$B$2:$B$67,$C$3,Marketing!$C$2:$C$67,G32,Marketing!$E$2:$E$67,$C$5) -> 61845 | F32: =IF(E32=0,0,SUMIFS(Sales!$L$2:$L$1321,Sales!$B$2:$B$1321,$C$3,Sales!$C$2:$C$1321,G32,Sales!$F$2:$F$1321,$C$5)/E32) -> 6.1952462 | G32: 10
B33: Nov | C33: =SUMIFS(Sales!$L$2:$L$1321,Sales!$B$2:$B$1321,$C$3,Sales!$C$2:$C$1321,G33,Sales!$E$2:$E$1321,$C$4,Sales!$F$2:$F$1321,$C$5,Sales!$G$2:$G$1321,$C$6) -> 0 | D33: =SUMIFS(Sales!$L$2:$L$1321,Sales!$B$2:$B$1321,$C$3-1,Sales!$C$2:$C$1321,G33,Sales!$E$2:$E$1321,$C$4,Sales!$F$2:$F$1321,$C$5,Sales!$G$2:$G$1321,$C$6) -> 422876 | E33: =SUMIFS(Marketing!$F$2:$F$67,Marketing!$B$2:$B$67,$C$3,Marketing!$C$2:$C$67,G33,Marketing!$E$2:$E$67,$C$5) -> 0 | F33: =IF(E33=0,0,SUMIFS(Sales!$L$2:$L$1321,Sales!$B$2:$B$1321,$C$3,Sales!$C$2:$C$1321,G33,Sales!$F$2:$F$1321,$C$5)/E33) -> 0 | G33: 11
B34: Dec | C34: =SUMIFS(Sales!$L$2:$L$1321,Sales!$B$2:$B$1321,$C$3,Sales!$C$2:$C$1321,G34,Sales!$E$2:$E$1321,$C$4,Sales!$F$2:$F$1321,$C$5,Sales!$G$2:$G$1321,$C$6) -> 0 | D34: =SUMIFS(Sales!$L$2:$L$1321,Sales!$B$2:$B$1321,$C$3-1,Sales!$C$2:$C$1321,G34,Sales!$E$2:$E$1321,$C$4,Sales!$F$2:$F$1321,$C$5,Sales!$G$2:$G$1321,$C$6) -> 544925 | E34: =SUMIFS(Marketing!$F$2:$F$67,Marketing!$B$2:$B$67,$C$3,Marketing!$C$2:$C$67,G34,Marketing!$E$2:$E$67,$C$5) -> 0 | F34: =IF(E34=0,0,SUMIFS(Sales!$L$2:$L$1321,Sales!$B$2:$B$1321,$C$3,Sales!$C$2:$C$1321,G34,Sales!$F$2:$F$1321,$C$5)/E34) -> 0 | G34: 12
B37: Category | C37: Net revenue | D37: Prior year | E37: YoY change | F37: Gross margin | G37: Return rate | H37: Units
B38: Tents & Shelter | C38: =SUMIFS(Sales!$L$2:$L$1321,Sales!$B$2:$B$1321,$C$3,Sales!$C$2:$C$1321,"<="&$C$7,Sales!$E$2:$E$1321,$C$4,Sales!$F$2:$F$1321,$C$5,Sales!$G$2:$G$1321,B38) -> 1105774 | D38: =SUMIFS(Sales!$L$2:$L$1321,Sales!$B$2:$B$1321,$C$3-1,Sales!$C$2:$C$1321,"<="&$C$7,Sales!$E$2:$E$1321,$C$4,Sales!$F$2:$F$1321,$C$5,Sales!$G$2:$G$1321,B38) -> 945467 | E38: =IF(D38=0,"",C38/D38-1) -> 0.16955325 | F38: =IF(C38=0,0,SUMIFS(Sales!$N$2:$N$1321,Sales!$B$2:$B$1321,$C$3,Sales!$C$2:$C$1321,"<="&$C$7,Sales!$E$2:$E$1321,$C$4,Sales!$F$2:$F$1321,$C$5,Sales!$G$2:$G$1321,B38)/C38) -> 0.46504982 | G38: =IFERROR(SUMIFS(Sales!$K$2:$K$1321,Sales!$B$2:$B$1321,$C$3,Sales!$C$2:$C$1321,"<="&$C$7,Sales!$E$2:$E$1321,$C$4,Sales!$F$2:$F$1321,$C$5,Sales!$G$2:$G$1321,B38)/SUMIFS(Sales!$J$2:$J$1321,Sales!$B$2:$B$1321,$C$3,Sales!$C$2:$C$1321,"<="&$C$7,Sales!$E$2:$E$1321,$C$4,Sales!$F$2:$F$1321,$C$5,Sales!$G$2:$G$1321,B38),0) -> 0.041177945 | H38: =SUMIFS(Sales!$I$2:$I$1321,Sales!$B$2:$B$1321,$C$3,Sales!$C$2:$C$1321,"<="&$C$7,Sales!$E$2:$E$1321,$C$4,Sales!$F$2:$F$1321,$C$5,Sales!$G$2:$G$1321,B38) -> 8456
B39: Backpacks | C39: =SUMIFS(Sales!$L$2:$L$1321,Sales!$B$2:$B$1321,$C$3,Sales!$C$2:$C$1321,"<="&$C$7,Sales!$E$2:$E$1321,$C$4,Sales!$F$2:$F$1321,$C$5,Sales!$G$2:$G$1321,B39) -> 944212 | D39: =SUMIFS(Sales!$L$2:$L$1321,Sales!$B$2:$B$1321,$C$3-1,Sales!$C$2:$C$1321,"<="&$C$7,Sales!$E$2:$E$1321,$C$4,Sales!$F$2:$F$1321,$C$5,Sales!$G$2:$G$1321,B39) -> 820493 | E39: =IF(D39=0,"",C39/D39-1) -> 0.15078617 | F39: =IF(C39=0,0,SUMIFS(Sales!$N$2:$N$1321,Sales!$B$2:$B$1321,$C$3,Sales!$C$2:$C$1321,"<="&$C$7,Sales!$E$2:$E$1321,$C$4,Sales!$F$2:$F$1321,$C$5,Sales!$G$2:$G$1321,B39)/C39) -> 0.54264614 | G39: =IFERROR(SUMIFS(Sales!$K$2:$K$1321,Sales!$B$2:$B$1321,$C$3,Sales!$C$2:$C$1321,"<="&$C$7,Sales!$E$2:$E$1321,$C$4,Sales!$F$2:$F$1321,$C$5,Sales!$G$2:$G$1321,B39)/SUMIFS(Sales!$J$2:$J$1321,Sales!$B$2:$B$1321,$C$3,Sales!$C$2:$C$1321,"<="&$C$7,Sales!$E$2:$E$1321,$C$4,Sales!$F$2:$F$1321,$C$5,Sales!$G$2:$G$1321,B39),0) -> 0.051088993 | H39: =SUMIFS(Sales!$I$2:$I$1321,Sales!$B$2:$B$1321,$C$3,Sales!$C$2:$C$1321,"<="&$C$7,Sales!$E$2:$E$1321,$C$4,Sales!$F$2:$F$1321,$C$5,Sales!$G$2:$G$1321,B39) -> 12378
B40: Apparel | C40: =SUMIFS(Sales!$L$2:$L$1321,Sales!$B$2:$B$1321,$C$3,Sales!$C$2:$C$1321,"<="&$C$7,Sales!$E$2:$E$1321,$C$4,Sales!$F$2:$F$1321,$C$5,Sales!$G$2:$G$1321,B40) -> 1062047 | D40: =SUMIFS(Sales!$L$2:$L$1321,Sales!$B$2:$B$1321,$C$3-1,Sales!$C$2:$C$1321,"<="&$C$7,Sales!$E$2:$E$1321,$C$4,Sales!$F$2:$F$1321,$C$5,Sales!$G$2:$G$1321,B40) -> 915813 | E40: =IF(D40=0,"",C40/D40-1) -> 0.1596767 | F40: =IF(C40=0,0,SUMIFS(Sales!$N$2:$N$1321,Sales!$B$2:$B$1321,$C$3,Sales!$C$2:$C$1321,"<="&$C$7,Sales!$E$2:$E$1321,$C$4,Sales!$F$2:$F$1321,$C$5,Sales!$G$2:$G$1321,B40)/C40) -> 0.60176527 | G40: =IFERROR(SUMIFS(Sales!$K$2:$K$1321,Sales!$B$2:$B$1321,$C$3,Sales!$C$2:$C$1321,"<="&$C$7,Sales!$E$2:$E$1321,$C$4,Sales!$F$2:$F$1321,$C$5,Sales!$G$2:$G$1321,B40)/SUMIFS(Sales!$J$2:$J$1321,Sales!$B$2:$B$1321,$C$3,Sales!$C$2:$C$1321,"<="&$C$7,Sales!$E$2:$E$1321,$C$4,Sales!$F$2:$F$1321,$C$5,Sales!$G$2:$G$1321,B40),0) -> 0.1036746 | H40: =SUMIFS(Sales!$I$2:$I$1321,Sales!$B$2:$B$1321,$C$3,Sales!$C$2:$C$1321,"<="&$C$7,Sales!$E$2:$E$1321,$C$4,Sales!$F$2:$F$1321,$C$5,Sales!$G$2:$G$1321,B40) -> 19790
B41: Footwear | C41: =SUMIFS(Sales!$L$2:$L$1321,Sales!$B$2:$B$1321,$C$3,Sales!$C$2:$C$1321,"<="&$C$7,Sales!$E$2:$E$1321,$C$4,Sales!$F$2:$F$1321,$C$5,Sales!$G$2:$G$1321,B41) -> 744196 | D41: =SUMIFS(Sales!$L$2:$L$1321,Sales!$B$2:$B$1321,$C$3-1,Sales!$C$2:$C$1321,"<="&$C$7,Sales!$E$2:$E$1321,$C$4,Sales!$F$2:$F$1321,$C$5,Sales!$G$2:$G$1321,B41) -> 638906 | E41: =IF(D41=0,"",C41/D41-1) -> 0.16479733 | F41: =IF(C41=0,0,SUMIFS(Sales!$N$2:$N$1321,Sales!$B$2:$B$1321,$C$3,Sales!$C$2:$C$1321,"<="&$C$7,Sales!$E$2:$E$1321,$C$4,Sales!$F$2:$F$1321,$C$5,Sales!$G$2:$G$1321,B41)/C41) -> 0.44405909 | G41: =IFERROR(SUMIFS(Sales!$K$2:$K$1321,Sales!$B$2:$B$1321,$C$3,Sales!$C$2:$C$1321,"<="&$C$7,Sales!$E$2:$E$1321,$C$4,Sales!$F$2:$F$1321,$C$5,Sales!$G$2:$G$1321,B41)/SUMIFS(Sales!$J$2:$J$1321,Sales!$B$2:$B$1321,$C$3,Sales!$C$2:$C$1321,"<="&$C$7,Sales!$E$2:$E$1321,$C$4,Sales!$F$2:$F$1321,$C$5,Sales!$G$2:$G$1321,B41),0) -> 0.12810852 | H41: =SUMIFS(Sales!$I$2:$I$1321,Sales!$B$2:$B$1321,$C$3,Sales!$C$2:$C$1321,"<="&$C$7,Sales!$E$2:$E$1321,$C$4,Sales!$F$2:$F$1321,$C$5,Sales!$G$2:$G$1321,B41) -> 9234
B42: Camp Kitchen | C42: =SUMIFS(Sales!$L$2:$L$1321,Sales!$B$2:$B$1321,$C$3,Sales!$C$2:$C$1321,"<="&$C$7,Sales!$E$2:$E$1321,$C$4,Sales!$F$2:$F$1321,$C$5,Sales!$G$2:$G$1321,B42) -> 560390 | D42: =SUMIFS(Sales!$L$2:$L$1321,Sales!$B$2:$B$1321,$C$3-1,Sales!$C$2:$C$1321,"<="&$C$7,Sales!$E$2:$E$1321,$C$4,Sales!$F$2:$F$1321,$C$5,Sales!$G$2:$G$1321,B42) -> 480000 | E42: =IF(D42=0,"",C42/D42-1) -> 0.16747917 | F42: =IF(C42=0,0,SUMIFS(Sales!$N$2:$N$1321,Sales!$B$2:$B$1321,$C$3,Sales!$C$2:$C$1321,"<="&$C$7,Sales!$E$2:$E$1321,$C$4,Sales!$F$2:$F$1321,$C$5,Sales!$G$2:$G$1321,B42)/C42) -> 0.51270544 | G42: =IFERROR(SUMIFS(Sales!$K$2:$K$1321,Sales!$B$2:$B$1321,$C$3,Sales!$C$2:$C$1321,"<="&$C$7,Sales!$E$2:$E$1321,$C$4,Sales!$F$2:$F$1321,$C$5,Sales!$G$2:$G$1321,B42)/SUMIFS(Sales!$J$2:$J$1321,Sales!$B$2:$B$1321,$C$3,Sales!$C$2:$C$1321,"<="&$C$7,Sales!$E$2:$E$1321,$C$4,Sales!$F$2:$F$1321,$C$5,Sales!$G$2:$G$1321,B42),0) -> 0.031241464 | H42: =SUMIFS(Sales!$I$2:$I$1321,Sales!$B$2:$B$1321,$C$3,Sales!$C$2:$C$1321,"<="&$C$7,Sales!$E$2:$E$1321,$C$4,Sales!$F$2:$F$1321,$C$5,Sales!$G$2:$G$1321,B42) -> 13229

Sheet Lists
A1: Year | B1: Region | C1: Channel | D1: Category
A2: 2026 | B2: All regions | C2: All channels | D2: All categories
A3: 2025 | B3: West | C3: Online store | D3: Tents & Shelter
B4: South | C4: Amazon | D4: Backpacks
B5: Northeast | C5: Retail store | D5: Apparel
B6: Midwest | D6: Footwear
D7: Camp Kitchen

Sheet How to use
B2: How to use this dashboard
B4: 1. On the Dashboard sheet, choose a Year, Region, Channel and Category from the blue dropdowns. Every KPI, chart and table updates.
B5: 2. Each month, paste the new monthly export at the bottom of the Sales sheet (one row per month × region × channel × category) and the ad spend per channel in the Marketing sheet. Both are Excel tables, so formulas extend automatically.
B6: 3. KPIs are year to date and compared with the same months of the previous year, so a part year is never compared with a full year.
B7: 4. The Calc sheet holds the helper formulas behind the charts — no need to edit it.
B9: Definitions: Net revenue = gross revenue − returns · Gross profit = net revenue − cost of goods sold · Gross margin = gross profit ÷ net revenue · Return rate = returns ÷ gross revenue · ROAS = net revenue ÷ ad spend.
B10: Colour key: blue dropdowns = choose from a list · blue numbers on data sheets = values you type · black = formulas.
B11: Harbor & Pine Outdoor Co. is a fictional company; all figures are demo data. Works in Excel 2010 or later, Excel for the web and LibreOffice. No macros.
